pyeugene/__init__.py
pyeugene/eugene.py
pyeugene/eugene_manager.py
pyeugene/eugene_proxy.py
pyeugene-1.0.1.dist-info/LICENSE
pyeugene-1.0.1.dist-info/METADATA
pyeugene-1.0.1.dist-info/WHEEL
pyeugene-1.0.1.dist-info/RECORD
