Metadata-Version: 2.1
Name: pyeugene
Version: 1.0.1
Summary: Eugene Investment & Securities Champion Open Api Python Wrapper
Author: Choh0401
Author-email: danielch0401@naver.com
Requires-Python: ==3.9.*
Classifier: Programming Language :: Python :: 3
Classifier: Programming Language :: Python :: 3.9
Requires-Dist: certifi (>=2023.7.22,<2024.0.0)
Requires-Dist: numpy (>=1.24.0,<2.0.0)
Requires-Dist: pandas (>=1.5.3,<2.0.0)
Requires-Dist: pypiwin32 (==223)
Requires-Dist: pyqt5 (>=5.15.9,<6.0.0)
Requires-Dist: pyqt5-qt5 (==5.15.2)
Requires-Dist: pyqt5-sip (>=12.12.2,<13.0.0)
Requires-Dist: python-dateutil (>=2.8.2,<3.0.0)
Requires-Dist: python-dotenv (>=1.0.0,<2.0.0)
Requires-Dist: pytz (>=2023.3.post1,<2024.0)
Requires-Dist: six (>=1.16.0,<2.0.0)
Requires-Dist: wincertstore (>=0.2,<0.3)
